{
  "scenes": [
    {
      "datetime": "2021-04-06T09:46:47+02:00",
      "location": "davos_rapid",
      "label": "emergency",
      "export_data": [
        {
          "start_datetime": "2021-04-06T09:46:17+02:00",
          "end_datetime": "2021-04-06T09:47:17+02:00",
          "zed_serial_number": 29089846,
          "start_frame_number": 18793,
          "end_frame_number": 19204,
          "original_file_id": 0
        },
        {
          "start_datetime": "2021-04-06T09:46:17+02:00",
          "end_datetime": "2021-04-06T09:47:17+02:00",
          "zed_serial_number": 24388529,
          "start_frame_number": 18699,
          "end_frame_number": 19111,
          "original_file_id": 1
        }
      ]
    }
  ],
  "original_files": [
    {
      "id": 0,
      "file_path": "ds20210406_sn29089846_ts070008.svo"
    },
    {
      "id": 1,
      "file_path": "ds20210406_sn24388529_ts070008.svo"
    }
  ]
}